[
  {
    "home_url": "https://www.redfin.com/TX/Austin/4614-Yellow-Rose-Trl-78749/home/31713336",
    "image_link": "https://ssl.cdn-redfin.com/system_files/media/1000905_JPG/genDesktopMapHomeCardUrl/item_40.jpg",
    "address": "4614 Yellow Rose Trl, Austin, TX 78749",
    "price": "$698,000",
    "beds": "4 beds",
    "baths": "2 baths",
    "area": "2,077"
  },
  {
    "home_url": "https://www.redfin.com/TX/Austin/10110-Hidden-Meadow-Dr-78750/home/32764235",
    "image_link": "https://ssl.cdn-redfin.com/system_files/media/999564_JPG/genDesktopMapHomeCardUrl/item_17.jpg",
    "address": "10110 Hidden Meadow Dr, Austin, TX 78750",
    "price": "$979,000",
    "beds": "5 beds",
    "baths": "4 baths",
    "area": "3,271"
  },
  {
    "home_url": "https://www.redfin.com/TX/Austin/11902-Hardwood-Trl-78750/home/32784941",
    "image_link": "https://ssl.cdn-redfin.com/system_files/media/997113_JPG/genDesktopMapHomeCardUrl/item_42.jpg",
    "address": "11902 Hardwood Trl, Austin, TX 78750",
    "price": "$360,000",
    "beds": "3 beds",
    "baths": "2 baths",
    "area": "1,505"
  },
  {
    "home_url": "https://www.redfin.com/TX/Austin/5120-Ganymede-Dr-78727/home/31563214",
    "image_link": "https://ssl.cdn-redfin.com/system_files/media/967977_JPG/genDesktopMapHomeCardUrl/item_3.jpg",
    "address": "5120 Ganymede Dr, Austin, TX 78727",
    "price": "$665,000",
    "beds": "3 beds",
    "baths": "2 baths",
    "area": "1,380"
  },
  {
    "home_url": "https://www.redfin.com/TX/Austin/1015-E-12th-St-78702/home/31048198",
    "image_link": "https://ssl.cdn-redfin.com/photo/92/islphoto/709/genIslnoResize.3613709_0.jpg",
    "address": "1015 E 12th St, Austin, TX 78702",
    "price": "$899,000",
    "beds": "4 beds",
    "baths": "3.5 baths",
    "area": "2,303"
  },
  {
    "home_url": "https://www.redfin.com/TX/Austin/10718-Pickfair-Dr-78750/home/31340233",
    "image_link": "https://ssl.cdn-redfin.com/photo/92/islphoto/996/genIslnoResize.4638996_1.jpg",
    "address": "10718 Pickfair Dr, Austin, TX 78750",
    "price": "$800,000",
    "beds": "3 beds",
    "baths": "2.5 baths",
    "area": "2,618"
  },
  {
    "home_url": "https://www.redfin.com/TX/Austin/906-E-Village-Ln-78758/home/31510296",
    "image_link": "https://ssl.cdn-redfin.com/photo/92/islphoto/584/genIslnoResize.1426584_0.jpg",
    "address": "906 E Village Ln, Austin, TX 78758",
    "price": "$275,000",
    "beds": "3 beds",
    "baths": "2.5 baths",
    "area": "1,372"
  },
  {
    "home_url": "https://www.redfin.com/TX/Austin/4245-Iriona-Bnd-78749/home/31777724",
    "image_link": "https://ssl.cdn-redfin.com/photo/92/islphoto/600/genIslnoResize.2618600_2.jpg",
    "address": "4245 Iriona Bnd, Austin, TX 78749",
    "price": "$559,000",
    "beds": "3 beds",
    "baths": "2 baths",
    "area": "1,714"
  },
  {
    "home_url": "https://www.redfin.com/TX/Austin/5203-Pryor-Ln-78734/home/31317059",
    "image_link": "https://ssl.cdn-redfin.com/photo/92/islphoto/536/genIslnoResize.4591536_0.jpg",
    "address": "5203 Pryor Ln, Austin, TX 78734",
    "price": "$619,995",
    "beds": "3 beds",
    "baths": "2.5 baths",
    "area": "1,702"
  },
  {
    "home_url": "https://www.redfin.com/TX/Austin/2220-Webberville-Rd-78702/unit-305/home/179147465",
    "image_link": "https://ssl.cdn-redfin.com/photo/92/islphoto/746/genIslnoResize.1607746_0.jpg",
    "address": "2220 Webberville Rd #305, Austin, TX 78702",
    "price": "$599,000",
    "beds": "2 beds",
    "baths": "2 baths",
    "area": "1,460"
  },
  {
    "home_url": "https://www.redfin.com/TX/Austin/10718-Pickfair-Dr-78750/home/31340233",
    "image_link": "https://ssl.cdn-redfin.com/photo/92/islphoto/996/genIslnoResize.4638996_1.jpg",
    "address": "10718 Pickfair Dr, Austin, TX 78750",
    "price": "$800,000",
    "beds": "3 beds",
    "baths": "2.5 baths",
    "area": "2,618"
  },
  {
    "home_url": "https://www.redfin.com/TX/Austin/906-E-Village-Ln-78758/home/31510296",
    "image_link": "https://ssl.cdn-redfin.com/photo/92/islphoto/584/genIslnoResize.1426584_0.jpg",
    "address": "906 E Village Ln, Austin, TX 78758",
    "price": "$275,000",
    "beds": "3 beds",
    "baths": "2.5 baths",
    "area": "1,372"
  },
  {
    "home_url": "https://www.redfin.com/TX/Austin/4245-Iriona-Bnd-78749/home/31777724",
    "image_link": "https://ssl.cdn-redfin.com/photo/92/islphoto/600/genIslnoResize.2618600_2.jpg",
    "address": "4245 Iriona Bnd, Austin, TX 78749",
    "price": "$559,000",
    "beds": "3 beds",
    "baths": "2 baths",
    "area": "1,714"
  },
  {
    "home_url": "https://www.redfin.com/TX/Austin/5203-Pryor-Ln-78734/home/31317059",
    "image_link": "https://ssl.cdn-redfin.com/photo/92/islphoto/536/genIslnoResize.4591536_0.jpg",
    "address": "5203 Pryor Ln, Austin, TX 78734",
    "price": "$619,995",
    "beds": "3 beds",
    "baths": "2.5 baths",
    "area": "1,702"
  },
  {
    "home_url": "https://www.redfin.com/TX/Austin/2220-Webberville-Rd-78702/unit-305/home/179147465",
    "image_link": "https://ssl.cdn-redfin.com/photo/92/islphoto/746/genIslnoResize.1607746_0.jpg",
    "address": "2220 Webberville Rd #305, Austin, TX 78702",
    "price": "$599,000",
    "beds": "2 beds",
    "baths": "2 baths",
    "area": "1,460"
  },
  {
    "home_url": "https://www.redfin.com/TX/Austin/12313-Emery-Oaks-Rd-78758/home/31547960",
    "image_link": "https://ssl.cdn-redfin.com/photo/92/islphoto/791/genIslnoResize.5690791_2.jpg",
    "address": "12313 Emery Oaks Rd, Austin, TX 78758",
    "price": "$335,000",
    "beds": "3 beds",
    "baths": "2 baths",
    "area": "1,144"
  },
  {
    "home_url": "https://www.redfin.com/TX/Austin/6809-Oasis-Pass-78732/home/31316648",
    "image_link": "https://ssl.cdn-redfin.com/photo/92/islphoto/128/genIslnoResize.1274128_0.jpg",
    "address": "6809 Oasis Pass, Austin, TX 78732",
    "price": "$9,500,000",
    "beds": "5 beds",
    "baths": "6 baths",
    "area": "7,621"
  },
  {
    "home_url": "https://www.redfin.com/TX/Austin/4701-Foster-Ranch-Rd-78735/home/31685235",
    "image_link": "https://ssl.cdn-redfin.com/photo/92/islphoto/528/genIslnoResize.4506528_0.jpg",
    "address": "4701 Foster Ranch Rd, Austin, TX 78735",
    "price": "$1,350,000",
    "beds": "5 beds",
    "baths": "1.5 baths",
    "area": "3,297"
  },
  {
    "home_url": "https://www.redfin.com/TX/Austin/2705-Deeringhill-Dr-78745/home/31740135",
    "image_link": "https://ssl.cdn-redfin.com/photo/92/islphoto/074/genIslnoResize.8538074_0.jpg",
    "address": "2705 Deeringhill Dr, Austin, TX 78745",
    "price": "$599,000",
    "beds": "3 beds",
    "baths": "2 baths",
    "area": "1,363"
  },
  {
    "home_url": "https://www.redfin.com/TX/Austin/7610-Meador-Ave-78752/unit-1/home/189838308",
    "image_link": "https://ssl.cdn-redfin.com/photo/92/islphoto/235/genIslnoResize.5715235_0.jpg",
    "address": "7610 Meador Ave #1, Austin, TX 78752",
    "price": "$589,000",
    "beds": "4 beds",
    "baths": "3 baths",
    "area": "1,942"
  },
  {
    "home_url": "https://www.redfin.com/TX/Austin/1811-Webberville-Rd-78721/unit-1209/home/187492661",
    "image_link": "https://ssl.cdn-redfin.com/photo/92/islphoto/386/genIslnoResize.6750386_0.jpg",
    "address": "1811 Webberville Rd #1209, Austin, TX 78721",
    "price": "$386,900",
    "beds": "2 beds",
    "baths": "2 baths",
    "area": "1,045"
  },
  {
    "home_url": "https://www.redfin.com/TX/Austin/126-Frederick-St-78704/home/31703620",
    "image_link": "https://ssl.cdn-redfin.com/photo/92/islphoto/785/genIslnoResize.1097785_0.jpg",
    "address": "126 Frederick St, Austin, TX 78704",
    "price": "$599,000",
    "beds": "3 beds",
    "baths": "2 baths",
    "area": "1,253"
  },
  {
    "home_url": "https://www.redfin.com/TX/Austin/2001-E-9th-St-78702/home/31370874",
    "image_link": "https://ssl.cdn-redfin.com/photo/92/islphoto/195/genIslnoResize.7516195_0.jpg",
    "address": "2001 E 9th St, Austin, TX 78702",
    "price": "$725,000",
    "beds": "3 beds",
    "baths": "2 baths",
    "area": "1,230"
  },
  {
    "home_url": "https://www.redfin.com/TX/Austin/13420-Lyndhurst-St-78729/unit-701/home/32674347",
    "image_link": "https://ssl.cdn-redfin.com/photo/92/islphoto/738/genIslnoResize.1247738_0.jpg",
    "address": "13420 Lyndhurst #701, Austin, TX 78729",
    "price": "$294,900",
    "beds": "3 beds",
    "baths": "2.5 baths",
    "area": "1,376"
  },
  {
    "home_url": "https://www.redfin.com/TX/Austin/6000-Cary-Dr-78757/home/31469382",
    "image_link": "https://ssl.cdn-redfin.com/photo/92/islphoto/762/genIslnoResize.8458762_0.jpg",
    "address": "6000 Cary Dr, Austin, TX 78757",
    "price": "$850,000",
    "beds": "3 beds",
    "baths": "2 baths",
    "area": "1,753"
  },
  {
    "home_url": "https://www.redfin.com/TX/Austin/6537-Tasajillo-Trl-78739/home/31972021",
    "image_link": "https://ssl.cdn-redfin.com/photo/92/islphoto/193/genIslnoResize.7115193_1.jpg",
    "address": "6537 Tasajillo Trl, Austin, TX 78739",
    "price": "$975,000",
    "beds": "4 beds",
    "baths": "3 baths",
    "area": "2,690"
  },
  {
    "home_url": "https://www.redfin.com/TX/Austin/2112-Lawnmont-Ave-78756/home/31461625",
    "image_link": "https://ssl.cdn-redfin.com/photo/92/islphoto/607/genIslnoResize.9334607_0.jpg",
    "address": "2112 Lawnmont Ave, Austin, TX 78756",
    "price": "$1,950,000",
    "beds": "5 beds",
    "baths": "4.5 baths",
    "area": "2,910"
  },
  {
    "home_url": "https://www.redfin.com/TX/Austin/1521-Sugarberry-Ln-78748/home/32318953",
    "image_link": "https://ssl.cdn-redfin.com/photo/92/islphoto/691/genIslnoResize.3037691_0.jpg",
    "address": "1521 Sugarberry Ln, Austin, TX 78748",
    "price": "$385,000",
    "beds": "3 beds",
    "baths": "2.5 baths",
    "area": "1,590"
  },
  {
    "home_url": "https://www.redfin.com/TX/Austin/5600-Overbrook-Dr-78723/home/31427146",
    "image_link": "https://ssl.cdn-redfin.com/photo/92/islphoto/853/genIslnoResize.4982853_0.jpg",
    "address": "5600 Overbrook Dr, Austin, TX 78723",
    "price": "$399,000",
    "beds": "3 beds",
    "baths": "1 bath",
    "area": "1,032"
  },
  {
    "home_url": "https://www.redfin.com/TX/Austin/10613-Watchful-Fox-Dr-78748/home/31829770",
    "image_link": "https://ssl.cdn-redfin.com/photo/92/islphoto/955/genIslnoResize.3031955_0.jpg",
    "address": "10613 Watchful Fox Dr, Austin, TX 78748",
    "price": "$429,000",
    "beds": "3 beds",
    "baths": "2.5 baths",
    "area": "1,534"
  },
  {
    "home_url": "https://www.redfin.com/TX/Austin/4511-Manzanillo-Dr-78749/home/31748826",
    "image_link": "https://ssl.cdn-redfin.com/photo/92/islphoto/234/genIslnoResize.4519234_0.jpg",
    "address": "4511 Manzanillo Dr, Austin, TX 78749",
    "price": "$415,000",
    "beds": "3 beds",
    "baths": "2 baths",
    "area": "1,270"
  },
  {
    "home_url": "https://www.redfin.com/TX/Austin/7515-Grover-Ave-78757/home/31480494",
    "image_link": "https://ssl.cdn-redfin.com/photo/92/islphoto/585/genIslnoResize.6861585_0.jpg",
    "address": "7515 Grover Ave, Austin, TX 78757",
    "price": "$625,000",
    "beds": "5 beds",
    "baths": "3.5 baths",
    "area": "1,926"
  },
  {
    "home_url": "https://www.redfin.com/TX/Austin/1304-Leona-St-78702/home/105446046",
    "image_link": "https://ssl.cdn-redfin.com/photo/92/islphoto/275/genIslnoResize.6300275_1.jpg",
    "address": "1304 Leona St, Austin, TX 78702",
    "price": "$1,175,000",
    "beds": "3 beds",
    "baths": "2.5 baths",
    "area": "2,235"
  },
  {
    "home_url": "https://www.redfin.com/TX/Austin/2702-S-2nd-St-78704/unit-A/home/185268481",
    "image_link": "https://ssl.cdn-redfin.com/photo/92/islphoto/289/genIslnoResize.7747289_0.jpg",
    "address": "2702 S 2nd St Unit A, Austin, TX 78704",
    "price": "$695,000",
    "beds": "3 beds",
    "baths": "2.5 baths",
    "area": "998"
  },
  {
    "home_url": "https://www.redfin.com/TX/West-Lake-Hills/2002-Yaupon-Valley-Rd-78746/home/44511153",
    "image_link": "https://ssl.cdn-redfin.com/photo/92/islphoto/180/genIslnoResize.2878180_1.jpg",
    "address": "2002 Yaupon Valley Rd, West Lake Hills, TX 78746",
    "price": "$3,900,000",
    "beds": "5 beds",
    "baths": "5.5 baths",
    "area": "4,607"
  },
  {
    "home_url": "https://www.redfin.com/TX/Austin/4302-Reynosa-Dr-78739/home/31821904",
    "image_link": "https://ssl.cdn-redfin.com/photo/92/islphoto/698/genIslnoResize.8717698_0.jpg",
    "address": "4302 Reynosa Dr, Austin, TX 78739",
    "price": "$515,000",
    "beds": "4 beds",
    "baths": "2 baths",
    "area": "2,080"
  },
  {
    "home_url": "https://www.redfin.com/TX/Austin/11500-Katy-Ln-78748/home/31840627",
    "image_link": "https://ssl.cdn-redfin.com/photo/92/islphoto/610/genIslnoResize.4719610_0.jpg",
    "address": "11500 Katy Ln, Austin, TX 78748",
    "price": "$949,999",
    "beds": "6 beds",
    "baths": "4.5 baths",
    "area": "5,759"
  },
  {
    "home_url": "https://www.redfin.com/TX/Austin/13700-Sage-Grouse-Dr-78729/unit-3201/home/137650571",
    "image_link": "https://ssl.cdn-redfin.com/photo/92/islphoto/274/genIslnoResize.1506274_1.jpg",
    "address": "13700 Sage Grouse Dr #3201, Austin, TX 78729",
    "price": "$339,990",
    "beds": "3 beds",
    "baths": "2.5 baths",
    "area": "1,831"
  },
  {
    "home_url": "https://www.redfin.com/TX/Austin/5226-Pine-Pl-78744/home/31645532",
    "image_link": "https://ssl.cdn-redfin.com/photo/92/islphoto/819/genIslnoResize.3771819_0.jpg",
    "address": "5226 Pine Pl, Austin, TX 78744",
    "price": "$300,000",
    "beds": "3 beds",
    "baths": "2 baths",
    "area": "1,333"
  },
  {
    "home_url": "https://www.redfin.com/TX/Austin/6709-Vine-St-78757/home/31479010",
    "image_link": "https://ssl.cdn-redfin.com/photo/92/islphoto/370/genIslnoResize.8584370_0.jpg",
    "address": "6709 Vine St, Austin, TX 78757",
    "price": "$599,000",
    "beds": "2 beds",
    "baths": "2 baths",
    "area": "1,404"
  },
  {
    "home_url": "https://www.redfin.com/TX/Austin/12406-Maypole-Bnd-78717/home/185232412",
    "image_link": "https://ssl.cdn-redfin.com/system_files/media/994255_JPG/genDesktopMapHomeCardUrl/item_1.jpg",
    "address": "12406 Maypole Bnd, Austin, TX 78717",
    "price": "$436,000",
    "beds": "3 beds",
    "baths": "2.5 baths",
    "area": "1,729"
  },
  {
    "home_url": "https://www.redfin.com/TX/Austin/11516-Oltons-Bluff-Cv-78754/home/31090991",
    "image_link": "https://ssl.cdn-redfin.com/system_files/media/991109_JPG/genDesktopMapHomeCardUrl/item_1.jpg",
    "address": "11516 Oltons Bluff Cv, Austin, TX 78754",
    "price": "$435,000",
    "beds": "3 beds",
    "baths": "2.5 baths",
    "area": "2,476"
  },
  {
    "home_url": "https://www.redfin.com/TX/Austin/1405-Hartford-Rd-78703/unit-101/home/30962427",
    "image_link": "https://ssl.cdn-redfin.com/system_files/media/911633_JPG/genDesktopMapHomeCardUrl/item_2.jpg",
    "address": "1405 Hartford Rd #101, Austin, TX 78703",
    "price": "$270,000",
    "beds": "0 beds",
    "baths": "1 bath",
    "area": "373"
  },
  {
    "home_url": "https://www.redfin.com/TX/Austin/5807-Wynona-Ave-78756/home/31465125",
    "image_link": "https://ssl.cdn-redfin.com/system_files/media/990627_JPG/genDesktopMapHomeCardUrl/item_1.jpg",
    "address": "5807 Wynona Ave, Austin, TX 78756",
    "price": "$639,000",
    "beds": "2 beds",
    "baths": "1 bath",
    "area": "962"
  },
  {
    "home_url": "https://www.redfin.com/TX/Austin/2109-Maxwell-Ln-78741/unit-B/home/108558574",
    "image_link": "https://ssl.cdn-redfin.com/system_files/media/989382_JPG/genDesktopMapHomeCardUrl/item_29.jpg",
    "address": "2109 Maxwell Ln Unit B, Austin, TX 78741",
    "price": "$339,000",
    "beds": "2 beds",
    "baths": "1.5 baths",
    "area": "888"
  },
  {
    "home_url": "https://www.redfin.com/TX/Austin/1606-Redd-St-78745/home/31709200",
    "image_link": "https://ssl.cdn-redfin.com/system_files/media/951637_JPG/genDesktopMapHomeCardUrl/item_41.jpg",
    "address": "1606 Redd St, Austin, TX 78745",
    "price": "$586,000",
    "beds": "2 beds",
    "baths": "2.5 baths",
    "area": "1,060"
  },
  {
    "home_url": "https://www.redfin.com/TX/Austin/6001-Bullard-Dr-78757/home/31471015",
    "image_link": "https://ssl.cdn-redfin.com/system_files/media/935760_JPG/genDesktopMapHomeCardUrl/item_5.jpg",
    "address": "6001 Bullard Dr, Austin, TX 78757",
    "price": "$3,500,000",
    "beds": "6 beds",
    "baths": "5 baths",
    "area": "5,281"
  },
  {
    "home_url": "https://www.redfin.com/TX/Austin/5213-Huisache-St-78751/home/169405299",
    "image_link": "https://ssl.cdn-redfin.com/system_files/media/949003_JPG/genDesktopMapHomeCardUrl/item_2.jpg",
    "address": "5213 Huisache St, Austin, TX 78751",
    "price": "$623,000",
    "beds": "3 beds",
    "baths": "3 baths",
    "area": "1,164"
  },
  {
    "home_url": "https://www.redfin.com/TX/Austin/1840-Burton-Dr-78741/unit-184/home/31627302",
    "image_link": "https://ssl.cdn-redfin.com/system_files/media/948426_JPG/genDesktopMapHomeCardUrl/item_11.jpg",
    "address": "1840 Burton Dr #184, Austin, TX 78741",
    "price": "$167,500",
    "beds": "1 bed",
    "baths": "1 bath",
    "area": "378"
  },
  {
    "home_url": "https://www.redfin.com/TX/Austin/1008-Muse-Ln-78702/unit-14/home/108544234",
    "image_link": "https://ssl.cdn-redfin.com/system_files/media/946292_JPG/genDesktopMapHomeCardUrl/item_1.jpg",
    "address": "1008 Muse Ln #14, Austin, TX 78702",
    "price": "$624,998",
    "beds": "3 beds",
    "baths": "2.5 baths",
    "area": "1,627"
  }
]
